s2tiling/__init__.py
s2tiling/core.py
s2tiling/data/__init__.py
s2tiling/data/s2_tiling.zip
s2tiling-0.1.1.dist-info/licenses/LICENSE
s2tiling-0.1.1.dist-info/licenses/NOTICE
tests/test_logic.py
tests/test_setup.py
s2tiling-0.1.1.dist-info/METADATA
s2tiling-0.1.1.dist-info/WHEEL
s2tiling-0.1.1.dist-info/top_level.txt
s2tiling-0.1.1.dist-info/RECORD
