Metadata-Version: 2.4
Name: s2tiling
Version: 0.1.1
Summary: Python library to resolve overlapping issues found in the Sentinel tiling grid.
Home-page: https://github.com/baloghk/s2tiling
Author: Balogh Károly
Author-email: Balogh Károly <balogh2k4@gmail.com>
Maintainer-email: Balogh Károly <balogh2k4@gmail.com>
License: MIT License
Project-URL: Homepage, https://github.com/baloghk/s2tiling
Project-URL: Bug Reports, https://github.com/baloghk/s2tiling/issues
Project-URL: Source, https://github.com/baloghk/s2tiling
Keywords: sentinel-2,satellite,mgrs,tiles,overlap,gis,geospatial
Classifier: Development Status :: 3 - Alpha
Classifier: Intended Audience :: Developers
Classifier: Topic :: Scientific/Engineering :: GIS
Classifier: License :: OSI Approved :: MIT License
Classifier: Programming Language :: Python :: 3
Classifier: Programming Language :: Python :: 3.9
Classifier: Programming Language :: Python :: 3.10
Classifier: Programming Language :: Python :: 3.11
Classifier: Programming Language :: Python :: 3.12
Classifier: Operating System :: OS Independent
Requires-Python: >=3.9
License-File: LICENSE
License-File: NOTICE
Requires-Dist: geopandas>=0.12.0
Requires-Dist: shapely>=2.0.0
Dynamic: author
Dynamic: home-page
Dynamic: license-file
Dynamic: requires-python
